mcp_mux-0.2.0.dist-info/licenses/LICENSE
mux/__init__.py
mux/__main__.py
mux/_version.py
mux/client.py
mux/config.py
mux/exceptions.py
mux/search.py
mux/server.py
mux/utils.py
mcp_mux-0.2.0.dist-info/METADATA
mcp_mux-0.2.0.dist-info/WHEEL
mcp_mux-0.2.0.dist-info/entry_points.txt
mcp_mux-0.2.0.dist-info/top_level.txt
mcp_mux-0.2.0.dist-info/RECORD
