Metadata-Version: 2.4
Name: mcp-mux
Version: 0.2.0
Summary: MCP router that simplifies tool access through semantic search
Author: Logan Donley
License: MIT
Classifier: Development Status :: 3 - Alpha
Classifier: Intended Audience :: Developers
Classifier: License :: OSI Approved :: MIT License
Classifier: Programming Language :: Python :: 3
Classifier: Programming Language :: Python :: 3.10
Classifier: Programming Language :: Python :: 3.11
Classifier: Programming Language :: Python :: 3.12
Classifier: Programming Language :: Python :: 3.13
Requires-Python: >=3.10
License-File: LICENSE
Requires-Dist: mcp[cli]>=1.12.3
Requires-Dist: fastembed>=0.4.2
Requires-Dist: fastapi>=0.115.6
Requires-Dist: uvicorn[standard]>=0.34.0
Requires-Dist: pydantic>=2.10.5
Requires-Dist: pydantic-settings>=2.7.1
Requires-Dist: httpx>=0.28.1
Requires-Dist: numpy>=2.2.2
Requires-Dist: websockets>=14.2
Requires-Dist: click>=8.1.8
Requires-Dist: rich>=13.9.5
Dynamic: license-file
